LICENSE
setup.py
youtube_searcher/__init__.py
youtube_searcher/parse.py
youtube_searcher/session.py
youtube_searcher.egg-info/PKG-INFO
youtube_searcher.egg-info/SOURCES.txt
youtube_searcher.egg-info/dependency_links.txt
youtube_searcher.egg-info/requires.txt
youtube_searcher.egg-info/top_level.txt