Metadata-Version: 1.0
Name: youtube-searcher
Version: 0.1.7
Summary: search youtube
Home-page: https://github.com/HelloChatterbox/youtube_searcher
Author: jarbasAI
Author-email: jarbasai@mailfence.com
License: Apache
Platform: UNKNOWN
